windsurf_throttle/__init__.py
windsurf_throttle/api.py
windsurf_throttle/app.py
windsurf_throttle/cli.py
windsurf_throttle-1.0.1.dist-info/METADATA
windsurf_throttle-1.0.1.dist-info/WHEEL
windsurf_throttle-1.0.1.dist-info/entry_points.txt
windsurf_throttle-1.0.1.dist-info/licenses/LICENSE
windsurf_throttle-1.0.1.dist-info/RECORD
