Metadata-Version: 2.4
Name: windsurf-throttle
Version: 1.0.1
Summary: Streamlit app for managing Windsurf credit caps
Project-URL: Homepage, https://github.com/PFPT-Internal/windsurf-throttle
Project-URL: Repository, https://github.com/PFPT-Internal/windsurf-throttle
Author-email: Your Name <your.email@example.com>
License: MIT
License-File: LICENSE
Keywords: credit,streamlit,throttle,windsurf
Classifier: Development Status :: 3 - Alpha
Classifier: Intended Audience :: Developers
Classifier: License :: OSI Approved :: MIT License
Classifier: Programming Language :: Python :: 3
Classifier: Programming Language :: Python :: 3.10
Classifier: Programming Language :: Python :: 3.11
Classifier: Programming Language :: Python :: 3.12
Requires-Python: >=3.10
Requires-Dist: httpx>=0.27.0
Requires-Dist: pandas>=2.0.0
Requires-Dist: python-dotenv>=1.0.0
Requires-Dist: streamlit>=1.40.0
Requires-Dist: watchdog>=4.0.0
Provides-Extra: dev
Requires-Dist: mypy>=1.13.0; extra == 'dev'
Requires-Dist: pre-commit>=4.0.0; extra == 'dev'
Requires-Dist: pytest>=8.0.0; extra == 'dev'
Requires-Dist: ruff>=0.8.0; extra == 'dev'
